odp_amsterdam/__init__.py
odp_amsterdam/const.py
odp_amsterdam/exceptions.py
odp_amsterdam/models.py
odp_amsterdam/odp_amsterdam.py
odp_amsterdam/py.typed
odp_amsterdam-6.1.1.dist-info/LICENSE
odp_amsterdam-6.1.1.dist-info/METADATA
odp_amsterdam-6.1.1.dist-info/WHEEL
odp_amsterdam-6.1.1.dist-info/RECORD
